{"options":{},"indexes":[{"v":{"$numberInt":"2"},"key":{"_id":{"$numberInt":"1"}},"name":"_id_","ns":"zimble.stripetransactions"},{"v":{"$numberInt":"2"},"key":{"transactionId":{"$numberInt":"1"}},"name":"transactionId_1","ns":"zimble.stripetransactions","background":true},{"v":{"$numberInt":"2"},"key":{"amount":{"$numberInt":"1"}},"name":"amount_1","ns":"zimble.stripetransactions","background":true},{"v":{"$numberInt":"2"},"key":{"description":{"$numberInt":"1"}},"name":"description_1","ns":"zimble.stripetransactions","background":true}],"uuid":"fa96e065e1704a6ba370428bad051785"}